LICENSE
MANIFEST.in
README.md
setup.py
getsub/__init__.py
getsub/__version__.py
getsub/constants.py
getsub/main.py
getsub/models.py
getsub/util.py
getsub.egg-info/PKG-INFO
getsub.egg-info/SOURCES.txt
getsub.egg-info/dependency_links.txt
getsub.egg-info/entry_points.txt
getsub.egg-info/not-zip-safe
getsub.egg-info/requires.txt
getsub.egg-info/top_level.txt
getsub/downloader/__init__.py
getsub/downloader/downloader.py
getsub/downloader/zimuku.py
getsub/downloader/zimuzu.py
tests/__init__.py
tests/integration/__init__.py
tests/integration/test_downloaders.py
tests/integration/test_main.py
tests/integration/test_zimuku.py
tests/unit/__init__.py
tests/unit/test_downloader.py
tests/unit/getsubtitles/__init__.py
tests/unit/getsubtitles/test_get_videos.py
tests/unit/getsubtitles/test_process_archive.py
tests/unit/util/__init__.py
tests/unit/util/test_choose.py
tests/unit/util/test_extract_name.py
tests/unit/util/test_get_file_list.py
tests/unit/util/test_guess_subtitle.py
tests/unit/util/test_p7zip.py