Metadata-Version: 1.0
Name: getsub
Version: 1.7.7
Summary: download subtitles easily
Home-page: UNKNOWN
Author: gyh1621
Author-email: guoyh01@gmail.com
License: MIT
Platform: UNKNOWN
